<?xml version="1.0" encoding="utf-8"?>
<Facts>
    <Fact id="tesla">
        <Description value="Tesla Model S"/>
        <Evals>
            <Eval id="family">false</Eval>
            <Eval id="money">true</Eval>
            <Eval id="comfort">true</Eval>
            <Eval id="luxury">true</Eval>
            <Eval id="ecological">true</Eval>
        </Evals>
    </Fact>
    <Fact id="seat">
        <Description value="Seat Leon"/>
        <Evals>
            <Eval id="family">false</Eval>
            <Eval id="money">false</Eval>
            <Eval id="comfort">true</Eval>
            <Eval id="luxury">false</Eval>
            <Eval id="ecological">false</Eval>
        </Evals>
    </Fact>
    <Fact id="porsche">
        <Description value="Porsche 911"/>
        <Evals>
            <Eval id="family">false</Eval>
            <Eval id="money">true</Eval>
            <Eval id="comfort">false</Eval>
            <Eval id="luxury">false</Eval>
            <Eval id="ecological">false</Eval>
        </Evals>
    </Fact>
    <Fact id="ford">
        <Description value="Ford Mondeo"/>
        <Evals>
            <Eval id="family">true</Eval>
            <Eval id="money">true</Eval>
            <Eval id="comfort">false</Eval>
            <Eval id="luxury">false</Eval>
            <Eval id="ecological">true</Eval>
        </Evals>
    </Fact>
    <Fact id="toyota">
        <Description value="Toyota Prius"/>
        <Evals>
            <Eval id="family">false</Eval>
            <Eval id="money">false</Eval>
            <Eval id="comfort">false</Eval>
            <Eval id="luxury">false</Eval>
            <Eval id="ecological">true</Eval>
        </Evals>
    </Fact>
    <Fact id="mercedes">
        <Description value="Mercedes S-class"/>
        <Evals>
            <Eval id="family">true</Eval>
            <Eval id="money">true</Eval>
            <Eval id="comfort">true</Eval>
            <Eval id="luxury">true</Eval>
            <Eval id="ecological">true</Eval>
        </Evals>
    </Fact>
    <Fact id="lamborghini">
        <Description value="Lamborghini Aventador"/>
        <Evals>
            <Eval id="family">false</Eval>
            <Eval id="money">true</Eval>
            <Eval id="comfort">false</Eval>
            <Eval id="luxury">true</Eval>
            <Eval id="ecological">false</Eval>
        </Evals>
    </Fact>
</Facts>